tcp_client.cpython-310-x86_64-linux-gnu.so
networking_tcp_client-0.4.dist-info/METADATA
networking_tcp_client-0.4.dist-info/top_level.txt
networking_tcp_client-0.4.dist-info/RECORD
networking_tcp_client-0.4.dist-info/WHEEL
