Metadata-Version: 2.1
Name: networking-tcp-client
Version: 0.4
Summary: Extension providing a basic tcp client for making connections, receiving and sending packets in C.
